fulladder/fulladder.v
module fulladder(a,b,cin,sum,out);
input a, b, cin;
output reg sum, out;
always @(*)
begin
 sum = a ^ b ^ cin;
 out = (a & b)|(cin&b) |(cin&a);

 end

endmodule

fulladder/fulladder_tb.v
`include "fulladder.v"
`timescale 1ns / 1ps

module fulladder_tb;
reg a,b,cin;
wire sum,out;
fulladder aud1(a,b,cin,sum,out);
initial begin 
$dumpfile("fulladder_tb.vcd");
$dumpvars(0,fulladder_tb);

a=0; b=0; cin=0; #10;
a=0; b=0; cin=1; #10;
a=0; b=1; cin=0; #10;
a=0; b=1; cin=1; #10;
a=1; b=0; cin=0; #10;
a=1; b=0; cin=1; #10;
a=1; b=1; cin=0; #10;
a=1; b=1; cin=1; #10;

end 
initial $monitor("time=%g,a=%d,b=%b,cin=%d,sum=%d,out=%d",$time,a,b,cin,sum,out);
initial #120 $finish;
endmodule

fulladder/fulladder_tb.vcd
$date
	Sun Aug 20 16:13:26 2023
$end
$version
	Icarus Verilog
$end
$timescale
	1ps
$end
$scope module fulladder_tb $end
$var wire 1 ! sum $end
$var wire 1 " out $end
$var reg 1 # a $end
$var reg 1 $ b $end
$var reg 1 % cin $end
$scope module aud1 $end
$var wire 1 # a $end
$var wire 1 $ b $end
$var wire 1 % cin $end
$var reg 1 " out $end
$var reg 1 ! sum $end
$upscope $end
$upscope $end
$enddefinitions $end
#0
$dumpvars
0%
0$
0#
0"
0!
$end
#10000
1!
1%
#20000
0%
1$
#30000
1"
0!
1%
#40000
0"
1!
0%
0$
1#
#50000
1"
0!
1%
#60000
0%
1$
#70000
1!
1%
