halfadder/halfadder.v
module halfadder(a,b,sum,carry);
input a,b;
output sum,carry;

assign sum=a ^ b;
assign carry= a & b;

endmodule

halfadder/halfadder_tb.v
`include "halfadder.v"


module halfadder_tb();

reg a,b;
wire sum,carry;
halfadder H1(a,b,sum,carry);
initial begin
$dumpfile("halfadder_tb.vcd");
$dumpvars(0,halfadder_tb);

a=0; b=0;#10;
end
always #1 b=b+1;
always #2 a=a+1;
initial $monitor("a=%b,b=%b,sum=%b,carry=%b",a,b,sum,carry);
initial #8 $finish;
endmodule

halfadder/halfadder_tb.vcd
$date
	Tue Aug 22 14:41:29 2023
$end
$version
	Icarus Verilog
$end
$timescale
	1s
$end
$scope module halfadder_tb $end
$var wire 1 ! sum $end
$var wire 1 " carry $end
$var reg 1 # a $end
$var reg 1 $ b $end
$scope module H1 $end
$var wire 1 # a $end
$var wire 1 $ b $end
$var wire 1 " carry $end
$var wire 1 ! sum $end
$upscope $end
$upscope $end
$enddefinitions $end
#0
$dumpvars
0$
0#
0"
0!
$end
#1
1!
1$
#2
0$
1#
#3
0!
1"
1$
#4
0"
0$
0#
#5
1!
1$
#6
0$
1#
#7
0!
1"
1$
#8
0"
0$
0#
